hl7/__init__.py
hl7/accessor.py
hl7/client.py
hl7/containers.py
hl7/datatypes.py
hl7/exceptions.py
hl7/parser.py
hl7/util.py
hl7/version.py
hl7/mllp/__init__.py
hl7/mllp/exceptions.py
hl7/mllp/streams.py
hl7-0.4.3.dist-info/AUTHORS
hl7-0.4.3.dist-info/LICENSE
hl7-0.4.3.dist-info/METADATA
hl7-0.4.3.dist-info/WHEEL
hl7-0.4.3.dist-info/entry_points.txt
hl7-0.4.3.dist-info/top_level.txt
hl7-0.4.3.dist-info/zip-safe
hl7-0.4.3.dist-info/RECORD
